pimterm/__init__.py
pimterm/main.py
pimterm-1.2.1.dist-info/LICENSE
pimterm-1.2.1.dist-info/METADATA
pimterm-1.2.1.dist-info/WHEEL
pimterm-1.2.1.dist-info/entry_points.txt
pimterm-1.2.1.dist-info/top_level.txt
pimterm-1.2.1.dist-info/RECORD
