Metadata-Version: 2.1
Name: pimterm
Version: 1.2.1
Summary: A simple Python package that helps you find the command you need.
Home-page: UNKNOWN
Author: Pim Verleg
Author-email: pim_iets@hotmail.com
License: MIT
Platform: UNKNOWN
Classifier: Programming Language :: Python :: 3
Classifier: License :: OSI Approved :: MIT License
Classifier: Operating System :: OS Independent
Requires-Python: >=3.6
License-File: LICENSE
Requires-Dist: openai
